tfr_scraper/__init__.py
tfr_scraper/tfr_scraper.py
tfr_scraper-0.0.8.dist-info/LICENSE
tfr_scraper-0.0.8.dist-info/METADATA
tfr_scraper-0.0.8.dist-info/WHEEL
tfr_scraper-0.0.8.dist-info/top_level.txt
tfr_scraper-0.0.8.dist-info/RECORD
