Metadata-Version: 2.1
Name: tfr-scraper
Version: 0.0.8
Summary: FAA TFR Scraper
Home-page: https://github.com/Jxck-S/TFR-Scraper/tree/main
Author: Jack Sweeney
License: UNKNOWN
Project-URL: Bug Tracker, https://github.com/Jxck-S/TFR-Scraper/issues
Platform: UNKNOWN
Classifier: Programming Language :: Python :: 3
Classifier: License :: OSI Approved :: MIT License
Classifier: Operating System :: OS Independent
Requires-Python: >=3.6
License-File: LICENSE
Requires-Dist: untangle
Requires-Dist: pandas
Requires-Dist: html-table-parser-python3
